CMakeLists.txt
LICENSE
MANIFEST.in
README.md
pyproject.toml
setup.cfg
setup.py
aivalut/CMakeLists.txt
aivalut/script/CMakeLists.txt
aivalut/src/CMakeLists.txt
aivalut/test/CMakeLists.txt
src/__init__.py
src/main.cpp
src/aijack/__init__.py
src/aijack.egg-info/PKG-INFO
src/aijack.egg-info/SOURCES.txt
src/aijack.egg-info/dependency_links.txt
src/aijack.egg-info/not-zip-safe
src/aijack.egg-info/requires.txt
src/aijack.egg-info/top_level.txt
src/aijack/attack/__init__.py
src/aijack/attack/base_attack.py
src/aijack/attack/backdoor/__init__.py
src/aijack/attack/backdoor/dba.py
src/aijack/attack/backdoor/modelreplacement.py
src/aijack/attack/evasion/__init__.py
src/aijack/attack/evasion/diva.py
src/aijack/attack/evasion/evasion_attack.py
src/aijack/attack/evasion/fgsm.py
src/aijack/attack/freerider/__init__.py
src/aijack/attack/freerider/freerider.py
src/aijack/attack/inversion/__init__.py
src/aijack/attack/inversion/gan_attack.py
src/aijack/attack/inversion/generator_attack.py
src/aijack/attack/inversion/gradientinversion.py
src/aijack/attack/inversion/gradientinversion_server.py
src/aijack/attack/inversion/mi_face.py
src/aijack/attack/inversion/utils/__init__.py
src/aijack/attack/inversion/utils/datarepextractor.py
src/aijack/attack/inversion/utils/distance.py
src/aijack/attack/inversion/utils/regularization.py
src/aijack/attack/inversion/utils/utils.py
src/aijack/attack/labelleakage/__init__.py
src/aijack/attack/labelleakage/normattack.py
src/aijack/attack/membership/__init__.py
src/aijack/attack/membership/membership_inference.py
src/aijack/attack/membership/utils.py
src/aijack/attack/poison/__init__.py
src/aijack/attack/poison/history.py
src/aijack/attack/poison/label_flip.py
src/aijack/attack/poison/mapf.py
src/aijack/attack/poison/poison_attack.py
src/aijack/collaborative/__init__.py
src/aijack/collaborative/utils.py
src/aijack/collaborative/core/__init__.py
src/aijack/collaborative/core/api.py
src/aijack/collaborative/core/client.py
src/aijack/collaborative/core/server.py
src/aijack/collaborative/core/utils.py
src/aijack/collaborative/dsfl/__init__.py
src/aijack/collaborative/dsfl/api.py
src/aijack/collaborative/dsfl/client.py
