Metadata-Version: 2.1
Name: aijack
Version: 0.0.1b2
Summary: Security and Privacy Risk Simulator for Machine Learning
Author: Hideaki Takahashi
License:                                  Apache License
License-File: LICENSE
Requires-Dist: numpy
Requires-Dist: pandas
Requires-Dist: scikit-learn
Requires-Dist: torch>=1.11.0
Requires-Dist: torchvision
Requires-Dist: opencv-python
Requires-Dist: pybind11
Requires-Dist: pybind11[global]
Requires-Dist: matplotlib
Requires-Dist: mpi4py
Requires-Dist: statsmodels
